evoeval/__init__.py
evoeval/_version.py
evoeval/data.py
evoeval/evaluate.py
evoeval/eval_test/__init__.py
evoeval/eval_test/_creative_special_oracle.py
evoeval/eval_test/_difficult_special_oracle.py
evoeval/eval_test/_he_special_oracle.py
evoeval/eval_test/_subtle_special_oracle.py
evoeval-0.1.0.dist-info/LICENSE
evoeval-0.1.0.dist-info/METADATA
evoeval-0.1.0.dist-info/WHEEL
evoeval-0.1.0.dist-info/entry_points.txt
evoeval-0.1.0.dist-info/top_level.txt
evoeval-0.1.0.dist-info/RECORD
