Metadata-Version: 2.1
Name: evoeval
Version: 0.1.0
Summary: "EvoEval: Evolving Coding Benchmarks via LLM"
Home-page: https://github.com/evo-eval/evoeval
License: Apache-2.0
Platform: any
Classifier: Operating System :: OS Independent
Classifier: Programming Language :: Python :: 3
Classifier: License :: OSI Approved :: Apache Software License
Requires-Python: >=3.9
License-File: LICENSE
Requires-Dist: wget >=3.2
Requires-Dist: tempdir >=0.7.1
Requires-Dist: multipledispatch >=0.6.0
Requires-Dist: appdirs >=1.4.4
Requires-Dist: numpy >=1.19.5
Requires-Dist: tqdm >=4.56.0
Requires-Dist: termcolor >=2.0.0
Requires-Dist: evalplus >=0.2.0
